django_server_controller/__init__.py
django_server_controller/controllers.py
django_server_controller/settings.py
django_server_controller/tests.py
django_server_controller/management/__init__.py
django_server_controller/management/commands/__init__.py
django_server_controller/management/commands/wsgi-server.py
django_server_controller/migrations/__init__.py
django_server_controller-0.5.4.dist-info/licenses/LICENSE
django_server_controller-0.5.4.dist-info/METADATA
django_server_controller-0.5.4.dist-info/WHEEL
django_server_controller-0.5.4.dist-info/top_level.txt
django_server_controller-0.5.4.dist-info/RECORD
