Metadata-Version: 2.4
Name: django-server-controller
Version: 0.5.4
Summary: Django server controllers, e.g. UwsgiController, GunicornController.
Author: rRR0VrFP
Maintainer: rRR0VrFP
License: MIT
Keywords: django-server-controller,UwsgiController,GunicornController
Classifier: Development Status :: 5 - Production/Stable
Classifier: Intended Audience :: Developers
Classifier: Topic :: Software Development :: Libraries :: Python Modules
Classifier: License :: OSI Approved :: MIT License
Classifier: Programming Language :: Python :: 3
Classifier: Programming Language :: Python :: 3 :: Only
License-File: LICENSE
Requires-Dist: django
Requires-Dist: psutil>=5.7.2
Requires-Dist: magic-import>=0.1.3
Requires-Dist: fastutils>=0.30.0
Requires-Dist: django-click>=2.2.0
Requires-Dist: click
Dynamic: author
Dynamic: classifier
Dynamic: description
Dynamic: description-content-type
Dynamic: keywords
Dynamic: license
Dynamic: license-file
Dynamic: maintainer
Dynamic: requires-dist
Dynamic: summary
